autodrive/__init__.py
autodrive/__init__.pyi
autodrive/_conn.py
autodrive/_conn.pyi
autodrive/_core.py
autodrive/_core.pyi
autodrive/_google_terms.py
autodrive/_google_terms.pyi
autodrive/_view.py
autodrive/_view.pyi
autodrive/connection.py
autodrive/connection.pyi
autodrive/drive.py
autodrive/drive.pyi
autodrive/dtypes.py
autodrive/dtypes.pyi
autodrive/formatting/__init__.py
autodrive/formatting/__init__.pyi
autodrive/formatting/_cell.py
autodrive/formatting/_cell.pyi
autodrive/formatting/_grid.py
autodrive/formatting/_grid.pyi
autodrive/formatting/_text.py
autodrive/formatting/_text.pyi
autodrive/formatting/format_rng.py
autodrive/formatting/format_rng.pyi
autodrive/formatting/format_tab.py
autodrive/formatting/format_tab.pyi
autodrive/gsheet.py
autodrive/gsheet.pyi
autodrive/interfaces.py
autodrive/interfaces.pyi
autodrive/range.py
autodrive/range.pyi
autodrive/tab.py
autodrive/tab.pyi
autodrive/typing.py
autodrive/typing.pyi
autodrive-0.6.3.dist-info/WHEEL
autodrive-0.6.3.dist-info/METADATA
autodrive-0.6.3.dist-info/RECORD
